zammadoo/__init__.py
zammadoo/articles.py
zammadoo/cache.py
zammadoo/client.py
zammadoo/groups.py
zammadoo/notifications.py
zammadoo/organizations.py
zammadoo/py.typed
zammadoo/resource.py
zammadoo/resources.py
zammadoo/roles.py
zammadoo/tags.py
zammadoo/tickets.py
zammadoo/time_accountings.py
zammadoo/users.py
zammadoo/utils.py
zammadoo-0.3.0.post0.dist-info/LICENSE
zammadoo-0.3.0.post0.dist-info/METADATA
zammadoo-0.3.0.post0.dist-info/WHEEL
zammadoo-0.3.0.post0.dist-info/RECORD
