Metadata-Version: 2.1
Name: zammadoo
Version: 0.3.0.post0
Summary: an object-oriented REST API client for zammad
Home-page: https://github.com/flashdagger/zammadoo
License: MIT
Keywords: zammad,rest,api
Author: flashdagger
Requires-Python: >=3.8,<4.0
Classifier: Development Status :: 4 - Beta
Classifier: License :: OSI Approved :: MIT License
Classifier: Operating System :: OS Independent
Classifier: Programming Language :: Python :: 3
Classifier: Programming Language :: Python :: 3.8
Classifier: Programming Language :: Python :: 3.9
Classifier: Programming Language :: Python :: 3.10
Classifier: Programming Language :: Python :: 3.11
Classifier: Programming Language :: Python :: 3.12
Classifier: Programming Language :: Python :: Implementation
Classifier: Programming Language :: Python :: Implementation :: CPython
Classifier: Programming Language :: Python :: Implementation :: PyPy
Requires-Dist: charset-normalizer (>=3.2,<4.0)
Requires-Dist: requests (>=2.28.2,<3.0.0)
Project-URL: Documentation, https://zammadoo.readthedocs.io/
Project-URL: Repository, https://github.com/flashdagger/zammadoo.git
